{
  "data": [
    {
      "id": 10,
      "age": 28,
      "name": "Chan Mccoy",
      "gender": "male",
      "email": "mccoychan@xurban.com",
      "phone": "+91 (865) 427-2249"
    },
    {
      "id": 11,
      "age": 38,
      "name": "Garcia Todd",
      "gender": "male",
      "email": "toddgarcia@xurban.com",
      "phone": "+91 (892) 406-2552"
    },
    {
      "id": 12,
      "age": 21,
      "name": "Graves Juana",
      "gender": "female",
      "email": "juanagraves@xurban.com",
      "phone": "+91 (943) 575-2080"
    },
    {
      "id": 13,
      "age": 27,
      "name": "Atkins Sears",
      "gender": "male",
      "email": "searsatkins@xurban.com",
      "phone": "+91 (913) 534-3162"
    },
    {
      "id": 14,
      "age": 29,
      "name": "Santos Lowery",
      "gender": "male",
      "email": "lowerysantos@xurban.com",
      "phone": "+91 (987) 569-3264"
    },
    {
      "id": 15,
      "age": 39,
      "name": "Mendoza Rosie",
      "gender": "female",
      "email": "rosiemendoza@xurban.com",
      "phone": "+91 (913) 536-3290"
    },
    {
      "id": 16,
      "age": 29,
      "name": "Waller Eunice",
      "gender": "female",
      "email": "eunicewaller@xurban.com",
      "phone": "+91 (941) 483-3951"
    },
    {
      "id": 17,
      "age": 37,
      "name": "Delgado Jarvis",
      "gender": "male",
      "email": "jarvisdelgado@xurban.com",
      "phone": "+91 (893) 488-2036"
    },
    {
      "id": 18,
      "age": 35,
      "name": "Holmes Becky",
      "gender": "female",
      "email": "beckyholmes@xurban.com",
      "phone": "+91 (830) 541-3584"
    },
    {
      "id": 19,
      "age": 34,
      "name": "Reeves Osborne",
      "gender": "male",
      "email": "osbornereeves@xurban.com",
      "phone": "+91 (888) 573-2373"
    },
    {
      "id": 20,
      "age": 22,
      "name": "Figueroa Moore",
      "gender": "male",
      "email": "moorefigueroa@xurban.com",
      "phone": "+91 (917) 424-3840"
    },
    {
      "id": 21,
      "age": 26,
      "name": "Wiggins Henry",
      "gender": "male",
      "email": "henrywiggins@xurban.com",
      "phone": "+91 (958) 446-2198"
    },
    {
      "id": 22,
      "age": 23,
      "name": "Thornton Sawyer",
      "gender": "male",
      "email": "sawyerthornton@xurban.com",
      "phone": "+91 (972) 436-2983"
    },
    {
      "id": 23,
      "age": 33,
      "name": "Cooper Juliana",
      "gender": "female",
      "email": "julianacooper@xurban.com",
      "phone": "+91 (923) 552-2536"
    },
    {
      "id": 24,
      "age": 22,
      "name": "Woods Fitzgerald",
      "gender": "male",
      "email": "fitzgeraldwoods@xurban.com",
      "phone": "+91 (865) 446-3428"
    },
    {
      "id": 25,
      "age": 34,
      "name": "Franks Vonda",
      "gender": "female",
      "email": "vondafranks@xurban.com",
      "phone": "+91 (840) 445-3987"
    },
    {
      "id": 26,
      "age": 31,
      "name": "Wilkerson Mccarthy",
      "gender": "male",
      "email": "mccarthywilkerson@xurban.com",
      "phone": "+91 (985) 433-2598"
    },
    {
      "id": 27,
      "age": 38,
      "name": "Potter Prince",
      "gender": "male",
      "email": "princepotter@xurban.com",
      "phone": "+91 (933) 527-3179"
    },
    {
      "id": 28,
      "age": 25,
      "name": "Richmond Annabelle",
      "gender": "female",
      "email": "annabellerichmond@xurban.com",
      "phone": "+91 (805) 511-3434"
    },
    {
      "id": 29,
      "age": 33,
      "name": "Saunders Robbie",
      "gender": "female",
      "email": "robbiesaunders@xurban.com",
      "phone": "+91 (822) 567-3653"
    },
    {
      "id": 30,
      "age": 23,
      "name": "Terry Jackson",
      "gender": "male",
      "email": "jacksonterry@xurban.com",
      "phone": "+91 (861) 430-3801"
    },
    {
      "id": 31,
      "age": 28,
      "name": "Graham Huber",
      "gender": "male",
      "email": "hubergraham@xurban.com",
      "phone": "+91 (889) 453-3728"
    },
    {
      "id": 32,
      "age": 24,
      "name": "Trevino Holden",
      "gender": "male",
      "email": "holdentrevino@xurban.com",
      "phone": "+91 (855) 418-3713"
    },
    {
      "id": 33,
      "age": 22,
      "name": "Byrd Bell",
      "gender": "male",
      "email": "bellbyrd@xurban.com",
      "phone": "+91 (847) 431-3376"
    },
    {
      "id": 34,
      "age": 24,
      "name": "Briggs Reeves",
      "gender": "male",
      "email": "reevesbriggs@xurban.com",
      "phone": "+91 (844) 485-3831"
    },
    {
      "id": 35,
      "age": 37,
      "name": "Jacobs Annie",
      "gender": "female",
      "email": "anniejacobs@xurban.com",
      "phone": "+91 (972) 499-2014"
    },
    {
      "id": 36,
      "age": 20,
      "name": "Lawson Erin",
      "gender": "female",
      "email": "erinlawson@xurban.com",
      "phone": "+91 (872) 509-2427"
    },
    {
      "id": 37,
      "age": 31,
      "name": "Hale Garrett",
      "gender": "male",
      "email": "garretthale@xurban.com",
      "phone": "+91 (865) 414-3695"
    },
    {
      "id": 38,
      "age": 38,
      "name": "Foreman Barker",
      "gender": "male",
      "email": "barkerforeman@xurban.com",
      "phone": "+91 (967) 440-3317"
    },
    {
      "id": 39,
      "age": 28,
      "name": "English Albert",
      "gender": "male",
      "email": "albertenglish@xurban.com",
      "phone": "+91 (920) 508-3122"
    },
    {
      "id": 40,
      "age": 25,
      "name": "Barr Patton",
      "gender": "male",
      "email": "pattonbarr@xurban.com",
      "phone": "+91 (919) 523-2198"
    },
    {
      "id": 41,
      "age": 30,
      "name": "Lang Monica",
      "gender": "female",
      "email": "monicalang@xurban.com",
      "phone": "+91 (815) 414-2010"
    },
    {
      "id": 42,
      "age": 24,
      "name": "Chen Bean",
      "gender": "male",
      "email": "beanchen@xurban.com",
      "phone": "+91 (929) 529-3474"
    },
    {
      "id": 43,
      "age": 23,
      "name": "Contreras Lawanda",
      "gender": "female",
      "email": "lawandacontreras@xurban.com",
      "phone": "+91 (814) 523-2771"
    },
    {
      "id": 44,
      "age": 37,
      "name": "Rios Barton",
      "gender": "male",
      "email": "bartonrios@xurban.com",
      "phone": "+91 (885) 489-3419"
    },
    {
      "id": 45,
      "age": 26,
      "name": "Ferguson Liz",
      "gender": "female",
      "email": "lizferguson@xurban.com",
      "phone": "+91 (912) 407-3965"
    },
    {
      "id": 46,
      "age": 33,
      "name": "Webster Alfreda",
      "gender": "female",
      "email": "alfredawebster@xurban.com",
      "phone": "+91 (875) 596-3227"
    },
    {
      "id": 47,
      "age": 30,
      "name": "Brady Wilda",
      "gender": "female",
      "email": "wildabrady@xurban.com",
      "phone": "+91 (925) 580-2935"
    },
    {
      "id": 48,
      "age": 34,
      "name": "Leon Lamb",
      "gender": "male",
      "email": "lambleon@xurban.com",
      "phone": "+91 (851) 460-2765"
    },
    {
      "id": 49,
      "age": 22,
      "name": "Buckner Tillman",
      "gender": "male",
      "email": "tillmanbuckner@xurban.com",
      "phone": "+91 (898) 529-2378"
    },
    {
      "id": 50,
      "age": 21,
      "name": "Estrada Best",
      "gender": "male",
      "email": "bestestrada@xurban.com",
      "phone": "+91 (871) 504-2658"
    },
    {
      "id": 51,
      "age": 30,
      "name": "Paul Hilda",
      "gender": "female",
      "email": "hildapaul@xurban.com",
      "phone": "+91 (901) 600-2708"
    },
    {
      "id": 52,
      "age": 31,
      "name": "Chandler Mcguire",
      "gender": "male",
      "email": "mcguirechandler@xurban.com",
      "phone": "+91 (980) 553-3096"
    },
    {
      "id": 53,
      "age": 40,
      "name": "Luna Virginia",
      "gender": "female",
      "email": "virginialuna@xurban.com",
      "phone": "+91 (910) 486-2811"
    },
    {
      "id": 54,
      "age": 22,
      "name": "Velez Tommie",
      "gender": "female",
      "email": "tommievelez@xurban.com",
      "phone": "+91 (926) 550-2984"
    },
    {
      "id": 55,
      "age": 38,
      "name": "Perkins Sybil",
      "gender": "female",
      "email": "sybilperkins@xurban.com",
      "phone": "+91 (969) 522-3778"
    },
    {
      "id": 56,
      "age": 37,
      "name": "Spencer Constance",
      "gender": "female",
      "email": "constancespencer@xurban.com",
      "phone": "+91 (826) 557-3694"
    },
    {
      "id": 57,
      "age": 20,
      "name": "Watts Cristina",
      "gender": "female",
      "email": "cristinawatts@xurban.com",
      "phone": "+91 (932) 473-3044"
    },
    {
      "id": 58,
      "age": 40,
      "name": "Sutton Guy",
      "gender": "male",
      "email": "guysutton@xurban.com",
      "phone": "+91 (865) 494-3467"
    },
    {
      "id": 59,
      "age": 31,
      "name": "Casey Marcie",
      "gender": "female",
      "email": "marciecasey@xurban.com",
      "phone": "+91 (855) 473-2374"
    },
    {
      "id": 60,
      "age": 22,
      "name": "Farley Duke",
      "gender": "male",
      "email": "dukefarley@xurban.com",
      "phone": "+91 (822) 465-3650"
    },
    {
      "id": 61,
      "age": 39,
      "name": "Leblanc Watts",
      "gender": "male",
      "email": "wattsleblanc@xurban.com",
      "phone": "+91 (923) 514-3673"
    },
    {
      "id": 62,
      "age": 23,
      "name": "Nash Mcclain",
      "gender": "male",
      "email": "mcclainnash@xurban.com",
      "phone": "+91 (850) 591-2538"
    },
    {
      "id": 63,
      "age": 26,
      "name": "Abbott Aileen",
      "gender": "female",
      "email": "aileenabbott@xurban.com",
      "phone": "+91 (925) 598-2262"
    },
    {
      "id": 64,
      "age": 22,
      "name": "Craft Latonya",
      "gender": "female",
      "email": "latonyacraft@xurban.com",
      "phone": "+91 (904) 427-3671"
    },
    {
      "id": 65,
      "age": 35,
      "name": "Savage Theresa",
      "gender": "female",
      "email": "theresasavage@xurban.com",
      "phone": "+91 (827) 452-2339"
    },
    {
      "id": 66,
      "age": 27,
      "name": "Hunter Tiffany",
      "gender": "female",
      "email": "tiffanyhunter@xurban.com",
      "phone": "+91 (826) 413-2859"
    },
    {
      "id": 67,
      "age": 21,
      "name": "Lawrence Gomez",
      "gender": "male",
      "email": "gomezlawrence@xurban.com",
      "phone": "+91 (812) 551-2139"
    },
    {
      "id": 68,
      "age": 39,
      "name": "Keller Navarro",
      "gender": "male",
      "email": "navarrokeller@xurban.com",
      "phone": "+91 (916) 589-3614"
    },
    {
      "id": 69,
      "age": 26,
      "name": "Richards Paige",
      "gender": "female",
      "email": "paigerichards@xurban.com",
      "phone": "+91 (837) 560-2910"
    },
    {
      "id": 70,
      "age": 35,
      "name": "Baldwin Bradley",
      "gender": "male",
      "email": "bradleybaldwin@xurban.com",
      "phone": "+91 (935) 435-2035"
    },
    {
      "id": 71,
      "age": 27,
      "name": "Webb Russo",
      "gender": "male",
      "email": "russowebb@xurban.com",
      "phone": "+91 (818) 536-2203"
    },
    {
      "id": 72,
      "age": 34,
      "name": "Barlow Evangelina",
      "gender": "female",
      "email": "evangelinabarlow@xurban.com",
      "phone": "+91 (955) 427-3234"
    },
    {
      "id": 73,
      "age": 28,
      "name": "Fisher Kim",
      "gender": "male",
      "email": "kimfisher@xurban.com",
      "phone": "+91 (988) 542-2496"
    },
    {
      "id": 74,
      "age": 23,
      "name": "Elliott Sonja",
      "gender": "female",
      "email": "sonjaelliott@xurban.com",
      "phone": "+91 (899) 408-2574"
    },
    {
      "id": 75,
      "age": 37,
      "name": "Scott Nora",
      "gender": "female",
      "email": "norascott@xurban.com",
      "phone": "+91 (908) 495-3315"
    },
    {
      "id": 76,
      "age": 31,
      "name": "Salas Spears",
      "gender": "male",
      "email": "spearssalas@xurban.com",
      "phone": "+91 (917) 546-3186"
    },
    {
      "id": 77,
      "age": 30,
      "name": "Dillon Odessa",
      "gender": "female",
      "email": "odessadillon@xurban.com",
      "phone": "+91 (841) 446-2904"
    },
    {
      "id": 78,
      "age": 28,
      "name": "Lindsay Norman",
      "gender": "male",
      "email": "normanlindsay@xurban.com",
      "phone": "+91 (904) 568-3830"
    },
    {
      "id": 79,
      "age": 32,
      "name": "Maxwell Callahan",
      "gender": "male",
      "email": "callahanmaxwell@xurban.com",
      "phone": "+91 (802) 457-2176"
    },
    {
      "id": 80,
      "age": 22,
      "name": "Melton Lela",
      "gender": "female",
      "email": "lelamelton@xurban.com",
      "phone": "+91 (825) 526-2776"
    },
    {
      "id": 81,
      "age": 31,
      "name": "Dickson Dudley",
      "gender": "male",
      "email": "dudleydickson@xurban.com",
      "phone": "+91 (900) 501-2109"
    },
    {
      "id": 82,
      "age": 23,
      "name": "Greer Ballard",
      "gender": "male",
      "email": "ballardgreer@xurban.com",
      "phone": "+91 (982) 593-3757"
    },
    {
      "id": 83,
      "age": 35,
      "name": "Oneil Blanca",
      "gender": "female",
      "email": "blancaoneil@xurban.com",
      "phone": "+91 (829) 508-2400"
    },
    {
      "id": 84,
      "age": 34,
      "name": "Hardy Caitlin",
      "gender": "female",
      "email": "caitlinhardy@xurban.com",
      "phone": "+91 (865) 572-3684"
    },
    {
      "id": 85,
      "age": 34,
      "name": "Bowers Angelique",
      "gender": "female",
      "email": "angeliquebowers@xurban.com",
      "phone": "+91 (816) 448-2580"
    },
    {
      "id": 86,
      "age": 26,
      "name": "Lucas Hogan",
      "gender": "male",
      "email": "hoganlucas@xurban.com",
      "phone": "+91 (893) 511-3783"
    },
    {
      "id": 87,
      "age": 30,
      "name": "Donaldson Felicia",
      "gender": "female",
      "email": "feliciadonaldson@xurban.com",
      "phone": "+91 (848) 563-2793"
    },
    {
      "id": 88,
      "age": 26,
      "name": "White Mcdaniel",
      "gender": "male",
      "email": "mcdanielwhite@xurban.com",
      "phone": "+91 (918) 460-2999"
    },
    {
      "id": 89,
      "age": 23,
      "name": "Crosby Maddox",
      "gender": "male",
      "email": "maddoxcrosby@xurban.com",
      "phone": "+91 (970) 578-2649"
    },
    {
      "id": 90,
      "age": 34,
      "name": "Beck Frederick",
      "gender": "male",
      "email": "frederickbeck@xurban.com",
      "phone": "+91 (937) 562-2454"
    },
    {
      "id": 91,
      "age": 37,
      "name": "Whitfield Rocha",
      "gender": "male",
      "email": "rochawhitfield@xurban.com",
      "phone": "+91 (974) 512-3477"
    },
    {
      "id": 92,
      "age": 24,
      "name": "Chase Doyle",
      "gender": "male",
      "email": "doylechase@xurban.com",
      "phone": "+91 (867) 472-3105"
    },
    {
      "id": 93,
      "age": 23,
      "name": "Garrison Hensley",
      "gender": "male",
      "email": "hensleygarrison@xurban.com",
      "phone": "+91 (970) 458-3662"
    },
    {
      "id": 95,
      "age": 21,
      "name": "Herman Joyce",
      "gender": "male",
      "email": "joyceherman@xurban.com",
      "phone": "+91 (866) 579-2257"
    },
    {
      "id": 96,
      "age": 39,
      "name": "Mcclain Georgina",
      "gender": "female",
      "email": "georginamcclain@xurban.com",
      "phone": "+91 (808) 584-2991"
    },
    {
      "id": 97,
      "age": 20,
      "name": "Curry Freida",
      "gender": "female",
      "email": "freidacurry@xurban.com",
      "phone": "+91 (926) 412-2262"
    },
    {
      "id": 98,
      "age": 27,
      "name": "Riggs Helen",
      "gender": "female",
      "email": "helenriggs@xurban.com",
      "phone": "+91 (870) 502-3577"
    },
    {
      "id": 99,
      "age": 36,
      "name": "Bell Heidi",
      "gender": "female",
      "email": "heidibell@xurban.com",
      "phone": "+91 (907) 433-3328"
    }
  ]
}